color_correction/__init__.py
color_correction/py.typed
color_correction/constant/__init__.py
color_correction/constant/color_checker.py
color_correction/constant/methods.py
color_correction/constant/yolov8_det.py
color_correction/core/__init__.py
color_correction/core/card_detection/__init__.py
color_correction/core/card_detection/base.py
color_correction/core/card_detection/det_yv8_onnx.py
color_correction/core/card_detection/mcc_det.py
color_correction/core/correction/__init__.py
color_correction/core/correction/_factory.py
color_correction/core/correction/affine_reg.py
color_correction/core/correction/base.py
color_correction/core/correction/least_squares.py
color_correction/core/correction/linear_reg.py
color_correction/core/correction/polynomial.py
color_correction/processor/__init__.py
color_correction/processor/detection.py
color_correction/schemas/__init__.py
color_correction/schemas/custom_types.py
color_correction/schemas/det_yv8.py
color_correction/schemas/device.py
color_correction/services/__init__.py
color_correction/services/color_correction.py
color_correction/services/correction_analyzer.py
color_correction/templates/base_report.html
color_correction/templates/column_description.html
color_correction/templates/script-report.js
color_correction/templates/style-report.css
color_correction/utils/__init__.py
color_correction/utils/correction.py
color_correction/utils/device_info.py
color_correction/utils/downloader.py
color_correction/utils/formater.py
color_correction/utils/geometry_processing.py
color_correction/utils/image_patch.py
color_correction/utils/image_processing.py
color_correction/utils/report_generator.py
color_correction/utils/visualization_utils.py
color_correction/utils/yolo_utils.py
color_correction-0.0.1rc5.dist-info/METADATA
color_correction-0.0.1rc5.dist-info/WHEEL
color_correction-0.0.1rc5.dist-info/RECORD
