Metadata-Version: 2.4
Name: color-correction
Version: 0.0.1rc5
Summary: help to do color correction on images based on color checker card classic 24 patch.
Project-URL: Homepage, https://github.com/agfianf/color-correction
Project-URL: Repository, https://github.com/agfianf/color-correction
Project-URL: Issues, https://github.com/agfianf/color-correction/issues
Author-email: magfianf <muhammadagfian96@gmail.com>
Maintainer-email: magfianf <muhammadagfian96@gmail.com>
Keywords: color consistency,color correction,color-consistency,color-correction,computer vision,vision
Classifier: Operating System :: OS Independent
Classifier: Programming Language :: Python :: 3 :: Only
Classifier: Programming Language :: Python :: 3.10
Classifier: Programming Language :: Python :: 3.11
Classifier: Programming Language :: Python :: 3.12
Classifier: Typing :: Typed
Requires-Python: >=3.10
Requires-Dist: colour-science>=0.4.6
Requires-Dist: httpx>=0.28.1
Requires-Dist: matplotlib>=3.10.1
Requires-Dist: onnx==1.17.0
Requires-Dist: onnxruntime==1.20.1
Requires-Dist: opencv-contrib-python>=4.11.0.86
Requires-Dist: pandas==2.2.3
Requires-Dist: pydantic-settings>=2.8.1
Requires-Dist: pydantic>=2.10.6
Requires-Dist: scikit-learn>=1.6.1
Requires-Dist: shapely>=2.0.7
